tfliteiorewriter/__init__.py
tfliteiorewriter/_version.py
tfliteiorewriter/main.py
tfliteiorewriter-1.1.0.dist-info/LICENSE
tfliteiorewriter-1.1.0.dist-info/METADATA
tfliteiorewriter-1.1.0.dist-info/WHEEL
tfliteiorewriter-1.1.0.dist-info/entry_points.txt
tfliteiorewriter-1.1.0.dist-info/top_level.txt
tfliteiorewriter-1.1.0.dist-info/RECORD
