Metadata-Version: 2.1
Name: tfliteiorewriter
Version: 1.1.0
Summary: This tool displays tflite signatures and rewrites the input/output OP name to the name of the signature. There is no need to install TensorFlow or TFLite.
Author-email: Katsuya Hyodo <rmsdh122@yahoo.co.jp>
License: MIT License
Project-URL: Homepage, https://github.com/PINTO0309/tflite-input-output-rewriter
Classifier: Programming Language :: Python :: 3
Requires-Python: >=3.8
License-File: LICENSE
Requires-Dist: requests
